model2graph/__init__.py
model2graph/constant.py
model2graph/extract.py
model2graph/transform.py
model2graph/utils/__init__.py
model2graph/utils/feature.py
model2graph-0.1.0.dist-info/METADATA
model2graph-0.1.0.dist-info/WHEEL
model2graph-0.1.0.dist-info/top_level.txt
model2graph-0.1.0.dist-info/RECORD
