Metadata-Version: 2.1
Name: model2graph
Version: 0.1.0
Summary: A package to convert deep learning models into graph structures
Home-page: https://github.com/odymit/model2graph
Author: anonymous
Author-email: anonymous@gmail.com
Classifier: Programming Language :: Python :: 3.11
Classifier: License :: OSI Approved :: MIT License
Classifier: Operating System :: POSIX :: Linux
Requires-Python: >3.10
Requires-Dist: alabaster==0.7.13
Requires-Dist: annotated-types==0.6.0
Requires-Dist: asttokens==2.4.1
Requires-Dist: autopep8==2.0.4
Requires-Dist: Babel==2.13.1
Requires-Dist: certifi==2023.11.17
Requires-Dist: charset-normalizer==3.3.2
Requires-Dist: click==8.1.7
Requires-Dist: cmake==3.27.7
Requires-Dist: decorator==5.1.1
Requires-Dist: dglgo==0.0.2
Requires-Dist: docutils==0.20.1
Requires-Dist: executing==2.0.1
Requires-Dist: filelock==3.13.1
Requires-Dist: idna==3.6
Requires-Dist: imagesize==1.4.1
Requires-Dist: ipython==8.18.1
Requires-Dist: isort==5.12.0
Requires-Dist: jedi==0.19.1
Requires-Dist: Jinja2==3.1.2
Requires-Dist: joblib==1.3.2
Requires-Dist: lit==17.0.6
Requires-Dist: littleutils==0.2.2
Requires-Dist: MarkupSafe==2.1.3
Requires-Dist: matplotlib-inline==0.1.6
Requires-Dist: mpmath==1.3.0
Requires-Dist: networkx==3.2.1
Requires-Dist: numpy==1.26.2
Requires-Dist: numpydoc==1.6.0
Requires-Dist: ogb==1.3.6
Requires-Dist: outdated==0.2.2
Requires-Dist: packaging==23.2
Requires-Dist: pandas==2.1.3
Requires-Dist: parso==0.8.3
Requires-Dist: pexpect==4.9.0
Requires-Dist: Pillow==10.1.0
Requires-Dist: prompt-toolkit==3.0.41
Requires-Dist: psutil==5.9.6
Requires-Dist: ptyprocess==0.7.0
Requires-Dist: pure-eval==0.2.2
Requires-Dist: pycodestyle==2.11.1
Requires-Dist: pydantic==2.5.2
Requires-Dist: pydantic-core==2.14.5
Requires-Dist: Pygments==2.17.2
Requires-Dist: pyparsing==3.1.1
Requires-Dist: python-dateutil==2.8.2
Requires-Dist: pytz==2023.3.post1
Requires-Dist: PyYAML==6.0.1
Requires-Dist: rdkit-pypi==2022.9.5
Requires-Dist: requests==2.31.0
Requires-Dist: ruamel.yaml==0.18.5
Requires-Dist: ruamel.yaml.clib==0.2.8
Requires-Dist: scikit-learn==1.3.2
Requires-Dist: scipy==1.11.4
Requires-Dist: six==1.16.0
Requires-Dist: snowballstemmer==2.2.0
Requires-Dist: Sphinx==7.2.6
Requires-Dist: sphinxcontrib-applehelp==1.0.7
Requires-Dist: sphinxcontrib-devhelp==1.0.5
Requires-Dist: sphinxcontrib-htmlhelp==2.0.4
Requires-Dist: sphinxcontrib-jsmath==1.0.1
Requires-Dist: sphinxcontrib-qthelp==1.0.6
Requires-Dist: sphinxcontrib-serializinghtml==1.1.9
Requires-Dist: stack-data==0.6.3
Requires-Dist: sympy==1.12
Requires-Dist: tabulate==0.9.0
Requires-Dist: threadpoolctl==3.2.0
Requires-Dist: torch==2.0.0
Requires-Dist: torch-geometric==2.4.0
Requires-Dist: torchvision==0.15.1
Requires-Dist: tqdm==4.66.1
Requires-Dist: traitlets==5.14.0
Requires-Dist: triton==2.0.0
Requires-Dist: typer==0.9.0
Requires-Dist: typing-extensions==4.8.0
Requires-Dist: tzdata==2023.3
Requires-Dist: urllib3==2.1.0
Requires-Dist: wcwidth==0.2.12
